auto_video_generator/__init__.py
auto_video_generator/cli.py
auto_video_generator/core.py
auto_video_generator/utils.py
auto_video_generator/assets/simhei.ttf
auto_video_generator/assets/ffmpeg/bin/ffmpeg.exe
auto_video_generator/assets/ffmpeg/bin/ffplay.exe
auto_video_generator/assets/ffmpeg/bin/ffprobe.exe
auto_video_generator/assets/ffmpeg/presets/libvpx-1080p.ffpreset
auto_video_generator/assets/ffmpeg/presets/libvpx-1080p50_60.ffpreset
auto_video_generator/assets/ffmpeg/presets/libvpx-360p.ffpreset
auto_video_generator/assets/ffmpeg/presets/libvpx-720p.ffpreset
auto_video_generator/assets/ffmpeg/presets/libvpx-720p50_60.ffpreset
auto_video_generator-1.0.0.dist-info/licenses/LICENSE
auto_video_generator-1.0.0.dist-info/METADATA
auto_video_generator-1.0.0.dist-info/WHEEL
auto_video_generator-1.0.0.dist-info/entry_points.txt
auto_video_generator-1.0.0.dist-info/top_level.txt
auto_video_generator-1.0.0.dist-info/RECORD
