Metadata-Version: 2.4
Name: auto-video-generator
Version: 1.0.0
Summary: 自动生成带字幕视频的工具，支持文字转语音、字幕同步和视频合成
Home-page: https://github.com/zgmurder/auto-video-generator
Author: zgmurder
Author-email: zgmurder <zgmurder1@gmail.com>
Maintainer-email: zgmurder <zgmurder1@gmail.com>
License: MIT
Project-URL: Homepage, https://github.com/zgmurder/auto-video-generator
Project-URL: Documentation, https://github.com/zgmurder/auto-video-generator#readme
Project-URL: Repository, https://github.com/zgmurder/auto-video-generator
Project-URL: Bug Tracker, https://github.com/zgmurder/auto-video-generator/issues
Keywords: video,subtitle,tts,text-to-speech,automation,multimedia
Classifier: Development Status :: 4 - Beta
Classifier: Intended Audience :: Developers
Classifier: Intended Audience :: End Users/Desktop
Classifier: License :: OSI Approved :: MIT License
Classifier: Operating System :: OS Independent
Classifier: Programming Language :: Python :: 3
Classifier: Programming Language :: Python :: 3.7
Classifier: Programming Language :: Python :: 3.8
Classifier: Programming Language :: Python :: 3.9
Classifier: Programming Language :: Python :: 3.10
Classifier: Programming Language :: Python :: 3.11
Classifier: Topic :: Multimedia :: Video
Classifier: Topic :: Software Development :: Libraries :: Python Modules
Requires-Python: >=3.7
License-File: LICENSE
Requires-Dist: edge-tts>=6.1.0
Requires-Dist: moviepy>=1.0.3
Requires-Dist: pydub>=0.25.1
Requires-Dist: tqdm>=4.64.0
Requires-Dist: Pillow>=9.0.0
Requires-Dist: numpy>=1.21.0
Requires-Dist: opencc-python-reimplemented>=0.1.7
Provides-Extra: dev
Requires-Dist: pytest>=7.0.0; extra == "dev"
Requires-Dist: pytest-cov>=4.0.0; extra == "dev"
Requires-Dist: black>=22.0.0; extra == "dev"
Requires-Dist: flake8>=5.0.0; extra == "dev"
Requires-Dist: mypy>=1.0.0; extra == "dev"
Provides-Extra: docs
Requires-Dist: sphinx>=5.0.0; extra == "docs"
Requires-Dist: sphinx-rtd-theme>=1.0.0; extra == "docs"
Dynamic: author
Dynamic: home-page
Dynamic: license-file
Dynamic: requires-python
